async_rest/__init__.py
async_rest/apps.py
async_rest/constants.py
async_rest/dispatcher.py
async_rest/helpers.py
async_rest/models.py
async_rest/serializers.py
async_rest/signals.py
async_rest/urls.py
async_rest/validators.py
async_rest/locale/.gitignore
async_rest/migrations/0001_initial.py
async_rest/migrations/__init__.py
async_rest/static/async_rest/.gitignore
async_rest/tests/__init__.py
async_rest/tests/test_basics.py
async_rest/tests/test_progress.py
async_rest/views/__init__.py
async_rest/views/rest.py
django_async_rest-1.0.0.dist-info/DESCRIPTION.rst
django_async_rest-1.0.0.dist-info/METADATA
django_async_rest-1.0.0.dist-info/metadata.json
django_async_rest-1.0.0.dist-info/RECORD
django_async_rest-1.0.0.dist-info/top_level.txt
django_async_rest-1.0.0.dist-info/WHEEL
