Metadata-Version: 2.0
Name: django-async-rest
Version: 1.0.0
Summary: A RESTful way of dealing with asynchronous tasks
Home-page: https://github.com/Netsach/django-async-rest
Author: P.A. Schembri
Author-email: pa.schembri@netsach.com
License: GPLv3
Platform: UNKNOWN
Requires-Dist: pytz (>=2015)
Requires-Dist: django (>=1.8)
Requires-Dist: django-jsonfield (==1.0.1)
Requires-Dist: djangorestframework (>=3.3)
Requires-Dist: sphinxcontrib-httpdomain (>=1.5)
